{
 "color": "#d97706",
 "creation": "2026-05-27 00:00:00.000000",
 "docstatus": 0,
 "doctype": "Number Card",
 "document_type": "Virtual Machine",
 "dynamic_filters_json": "[]",
 "filters_json": "[[\"Virtual Machine\",\"status\",\"=\",\"Pending\"]]",
 "function": "Count",
 "idx": 0,
 "is_public": 1,
 "is_standard": 1,
 "label": "Pending Virtual Machines",
 "modified": "2026-05-27 00:00:00.000000",
 "modified_by": "Administrator",
 "module": "Atlas",
 "name": "Pending Virtual Machines",
 "owner": "Administrator",
 "show_percentage_stats": 0,
 "stats_time_interval": "Daily",
 "type": "Document Type"
}
